README
setup.py
oarg/__init__.py
oarg/oarg.py
oarg.egg-info/PKG-INFO
oarg.egg-info/SOURCES.txt
oarg.egg-info/dependency_links.txt
oarg.egg-info/not-zip-safe
oarg.egg-info/top_level.txt