Metadata-Version: 1.1
Name: oarg
Version: 0.9.2
Summary: Command line simple argument parser
Home-page: https://github.com/erikperillo/oarg_py
Author: Erik Perillo
Author-email: erik.perillo@gmail.com
License: GPL3
Platform: UNKNOWN
Classifier: Programming Language :: Python :: 2.7
Classifier: Programming Language :: Python :: 3
